fatpack/__init__.py
fatpack/endurance.py
fatpack/racetrack.py
fatpack/rainflow.py
fatpack/stresscorrection.py
fatpack/test.py
fatpack-0.7.8.dist-info/LICENSE
fatpack-0.7.8.dist-info/METADATA
fatpack-0.7.8.dist-info/WHEEL
fatpack-0.7.8.dist-info/top_level.txt
fatpack-0.7.8.dist-info/RECORD
