Metadata-Version: 2.1
Name: fatpack
Version: 0.7.8
Summary: Fatigue analysis in python
Author-email: "Gunnstein T. Frøseth" <gunnstein@mailbox.org>
License: ISC License
Project-URL: repository, https://github.com/gunnstein/fatpack
Classifier: License :: OSI Approved :: ISC License (ISCL)
Classifier: Operating System :: OS Independent
Classifier: Programming Language :: Python
Classifier: Topic :: Scientific/Engineering
License-File: LICENSE
Requires-Dist: numpy
